{"cameraMode":{"drawMode":0,"name":"Shaded","section":"Shading Mode"},"sceneLighting":true,"audioPlay":false,"sceneViewState":{"showFog":true,"showMaterialUpdate":false,"showSkybox":true,"showFlares":true,"showImageEffects":true,"showParticleSystems":true},"in2DMode":false,"pivot":{"x":-6.146182537078857,"y":-26.33922576904297,"z":3.1787915229797365},"rotation":{"x":0.19457662105560304,"y":-0.6743361353874207,"z":0.19121675193309785,"w":0.6861844658851624},"size":24.525096893310548,"orthographic":false}